{
  "$schema": "https://developer.microsoft.com/json-schemas/spfx-build/package-solution.schema.json",
  "solution": {
    "name": "mega-menu-sp-fx-client-side-solution",
    "id": "8f49d75c-5a49-4657-b81b-0290f239350f",
    "version": "1.0.0.0",
    "includeClientSideAssets": true,
    "skipFeatureDeployment": true,
    "isDomainIsolated": false,
    "features": [
      {
        "title": "Application Extension - Deployment of custom action.",
        "description": "Deploys a custom action with ClientSideComponentId association",
        "id": "0d2345df-2a49-4ce9-ba2d-bee7ad3e7a02",
        "version": "1.0.0.0",
        "assets": {
          "elementManifests": [
            "elements.xml",
            "clientsideinstance.xml"
          ]
        }
      }
    ]
  },
  "paths": {
    "zippedPackage": "solution/mega-menu-sp-fx.sppkg"
  }
}
